noval/__init__.py
noval/const.py
noval/downloader.py
noval/extractor.py
noval/fiction_downloader.py
noval/main.py
noval/terminal.py
noval/utils.py
noval-2022.3.22.dist-info/LICENSE
noval-2022.3.22.dist-info/METADATA
noval-2022.3.22.dist-info/WHEEL
noval-2022.3.22.dist-info/entry_points.txt
noval-2022.3.22.dist-info/top_level.txt
noval-2022.3.22.dist-info/RECORD
