Metadata-Version: 2.1
Name: noval
Version: 2022.3.22
Summary: Configurable novel Downloader.
Home-page: https://github.com/zlj-zz/noval.git
Author: Zachary Zhang
Author-email: zlj19971222@outlook.com
License: UNKNOWN
Platform: UNKNOWN
Classifier: Programming Language :: Python :: 3
Classifier: Programming Language :: Python :: 3.8
Classifier: Programming Language :: Python :: 3.9
Classifier: Programming Language :: Python :: 3.10
Classifier: Topic :: System :: Shells
Classifier: License :: OSI Approved :: MIT License
Classifier: Operating System :: POSIX
Classifier: Operating System :: Unix
Classifier: Operating System :: MacOS
Classifier: Operating System :: Microsoft :: Windows
Requires-Python: >=3.8
License-File: LICENSE
Requires-Dist: requests
Requires-Dist: lxml
Requires-Dist: numpy
Requires-Dist: rich
